Metadata-Version: 2.1
Name: vcsparse
Version: 0.1.2
Summary: Generate fused and vectorizable kernels for sparse tensor programs on CPUs and GPUs
Home-page: https://github.com/tongzhou80/vcsparse
Author: Tong Zhou
Author-email: zt9465@gmail.com
Classifier: Programming Language :: Python :: 3
Classifier: License :: OSI Approved :: MIT License
Classifier: Operating System :: OS Independent
Requires-Python: >=3.9
Requires-Dist: ast-transforms
